circleci/__init__.py
circleci/api.py
circleci/error.py
circleci/experimental.py
circleci-1.1.3.dist-info/LICENSE
circleci-1.1.3.dist-info/METADATA
circleci-1.1.3.dist-info/WHEEL
circleci-1.1.3.dist-info/top_level.txt
circleci-1.1.3.dist-info/RECORD
