Metadata-Version: 2.1
Name: circleci
Version: 1.1.3
Summary: Python wrapper for the CircleCI API
Home-page: https://github.com/levlaz/circleci.py
Author: Lev Lazinskiy
Author-email: lev@levlaz.org
License: MIT
Keywords: circleci ci cd api sdk
Platform: UNKNOWN
Classifier: Development Status :: 5 - Production/Stable
Classifier: Intended Audience :: Developers
Classifier: Intended Audience :: System Administrators
Classifier: License :: OSI Approved :: MIT License
Classifier: Operating System :: OS Independent
Classifier: Topic :: Software Development :: Build Tools
Classifier: Topic :: Software Development :: Libraries :: Python Modules
Classifier: Topic :: Internet
Classifier: Programming Language :: Python :: 3
Classifier: Programming Language :: Python :: 3.6
Classifier: Programming Language :: Python :: 3 :: Only
Requires-Python: >=3
Requires-Dist: requests
